sci_plot_style/__init__.py
sci_plot_style/plot.py
sci_plot_style/styles/color/bright.mplstyle
sci_plot_style/styles/color/high-contrast.mplstyle
sci_plot_style/styles/color/high-vis.mplstyle
sci_plot_style/styles/color/light.mplstyle
sci_plot_style/styles/color/muted.mplstyle
sci_plot_style/styles/color/retro.mplstyle
sci_plot_style/styles/color/std-colors.mplstyle
sci_plot_style/styles/color/vibrant.mplstyle
sci_plot_style/styles/fonts/HarmonyOS_Sans.ttf
sci_plot_style/styles/fonts/TimesSong.ttf
sci_plot_style/styles/journals/ieee.mplstyle
sci_plot_style/styles/journals/ieee_ts.mplstyle
sci_plot_style/styles/journals/nature.mplstyle
sci_plot_style/styles/journals/nature_ts.mplstyle
sci_plot_style/styles/journals/notebook.mplstyle
sci_plot_style/styles/journals/scatter.mplstyle
sci_plot_style/styles/journals/scatter_ts.mplstyle
sci_plot_style/styles/journals/science.mplstyle
sci_plot_style/styles/languages/cjk-jp-font.mplstyle
sci_plot_style/styles/languages/cjk-kr-font.mplstyle
sci_plot_style/styles/languages/cjk-sc-font.mplstyle
sci_plot_style/styles/languages/cjk-tc-font.mplstyle
sci_plot_style/styles/languages/russian-font.mplstyle
sci_plot_style/styles/languages/turkish-font.mplstyle
sci_plot_style/styles/misc/grid.mplstyle
sci_plot_style/styles/misc/latex-sans.mplstyle
sci_plot_style/styles/misc/no-latex.mplstyle
sci_plot_style/styles/misc/pgf.mplstyle
sci_plot_style/styles/misc/sans.mplstyle
sci_plot_style-1.0.3.dist-info/METADATA
sci_plot_style-1.0.3.dist-info/WHEEL
sci_plot_style-1.0.3.dist-info/top_level.txt
sci_plot_style-1.0.3.dist-info/RECORD
