Metadata-Version: 2.1
Name: sci-plot-style
Version: 1.0.3
Summary: SCI style
Home-page: UNKNOWN
Author: Feifeng Wu
Author-email: wufeifeng_hust@163.com
License: GPLv3
Keywords: matplotlib
Platform: UNKNOWN
Classifier: Development Status :: 3 - Alpha
Classifier: Environment :: Console
Classifier: Operating System :: OS Independent
Requires-Python: >=3.6
Requires-Dist: matplotlib
